ccm_java8.py
ccm_java8-1.0.dist-info/LICENSE
ccm_java8-1.0.dist-info/METADATA
ccm_java8-1.0.dist-info/WHEEL
ccm_java8-1.0.dist-info/entry_points.txt
ccm_java8-1.0.dist-info/top_level.txt
ccm_java8-1.0.dist-info/RECORD
