Metadata-Version: 2.1
Name: ccm-java8
Version: 1.0
Summary: CCM extension that starts Cassandra (and related tools) under Java 8
Home-page: https://github.com/instaclustr/ccm-java8
Author: Adam Zegelin
Author-email: adam@instaclustr.com
License: UNKNOWN
Platform: UNKNOWN
Classifier: Development Status :: 5 - Production/Stable
Classifier: Environment :: Console
Classifier: Environment :: Plugins
Classifier: Environment :: MacOS X
Classifier: Intended Audience :: Developers
Classifier: License :: OSI Approved :: Apache Software License
Classifier: Topic :: Database
Requires-Dist: ccm
Requires-Dist: os-release
